stac2dcache/__init__.py
stac2dcache/__version__.py
stac2dcache/configure.py
stac2dcache/filesystem.py
stac2dcache/stac_io.py
stac2dcache/utils.py
stac2dcache/drivers/__init__.py
stac2dcache/drivers/base.py
stac2dcache/drivers/rasterio.py
stac2dcache/drivers/raw.py
stac2dcache/drivers/textfiles.py
tests/__init__.py
tests/test_filesystem.py
tests/test_lint.py
tests/test_stac_io.py
tests/test_utils.py
stac2dcache-0.4.0.dist-info/LICENSE
stac2dcache-0.4.0.dist-info/METADATA
stac2dcache-0.4.0.dist-info/NOTICE
stac2dcache-0.4.0.dist-info/WHEEL
stac2dcache-0.4.0.dist-info/top_level.txt
stac2dcache-0.4.0.dist-info/RECORD
