Metadata-Version: 2.1
Name: stac2dcache
Version: 0.4.0
Summary: Python tool to create and manipulate STAC catalogs on a dCache storage system
Home-page: https://github.com/NLeSC-GO-common-infrastructure/stac2dcache
Author: Team Atlas
Author-email: team-atlas@esciencecenter.nl
License: Apache Software License 2.0
Keywords: stac2dcache
Platform: UNKNOWN
Classifier: Development Status :: 2 - Pre-Alpha
Classifier: Intended Audience :: Developers
Classifier: License :: OSI Approved :: Apache Software License
Classifier: Natural Language :: English
Classifier: Programming Language :: Python :: 3
Classifier: Programming Language :: Python :: 3.7
Classifier: Programming Language :: Python :: 3.8
Classifier: Programming Language :: Python :: 3.9
Requires-Python: >=3.7
Requires-Dist: aiohttp
Requires-Dist: dcachefs (>=0.1.4)
Requires-Dist: fsspec
Requires-Dist: pystac (>=1.2)
Requires-Dist: urlpath
Requires-Dist: rasterio (==1.3.2)
Requires-Dist: rioxarray
Provides-Extra: test
Requires-Dist: pytest ; extra == 'test'
Requires-Dist: pytest-cov ; extra == 'test'
Requires-Dist: pycodestyle ; extra == 'test'
Provides-Extra: tutorial
Requires-Dist: pystac-client ; extra == 'tutorial'
Requires-Dist: matplotlib ; extra == 'tutorial'
